MANIFEST.in
README.rst
setup.py
bin/ca_tracker
bin/ca_tracker_1
bin/ca_tracker_2
ca_tracker/__init__.py
ca_tracker/abs_time.py
ca_tracker/cell_detect_2.py
ca_tracker/classify_cells.py
ca_tracker/compute_features.py
ca_tracker/export_overlays_with_labels.py
ca_tracker/extract_intensity.py
ca_tracker/helper.py
ca_tracker/idaf_image_processing.py
ca_tracker/idaf_io.py
ca_tracker/link_particles.py
ca_tracker/merge_tracking_data.py
ca_tracker/plot_profiles.py
ca_tracker.egg-info/PKG-INFO
ca_tracker.egg-info/SOURCES.txt
ca_tracker.egg-info/dependency_links.txt
ca_tracker.egg-info/not-zip-safe
ca_tracker.egg-info/pbr.json
ca_tracker.egg-info/requires.txt
ca_tracker.egg-info/top_level.txt
ca_tracker/cell_profiler/classifyCellProbability.cpproj
ca_tracker/cell_profiler/fg_bg_classifier_2.h5
ca_tracker/cell_profiler/fg_bg_classifier_3.h5
ca_tracker/config/config.json
ca_tracker/imagej/file_conversion_ui.ijm
ca_tracker/imagej/file_conversion_ui_2.ijm