Metadata-Version: 1.0
Name: ca-tracker
Version: 0.2.11
Summary: Package for cell segmentation, tracking, classification into asc negative and asc positive cells and calcium intensity measurements over time
Home-page: UNKNOWN
Author: Christoph Moehl, Image and Data Analysis Facility, German Center of Neurodegenerative Diseases, Bonn, Germany
Author-email: christoph.moehl@dzne.de
License: UNKNOWN
Platform: UNKNOWN
